{"nodes": [{"id": "lib_mockdata", "label": "Mock Data / Type Definitions", "file_type": "code", "source_file": "apps/desktop/src/lib/mockData.ts", "source_location": null, "source_url": null, "captured_at": null, "author": null, "contributor": null}, {"id": "mockData_AssessmentRow", "label": "AssessmentRow Interface", "file_type": "code", "source_file": "apps/desktop/src/lib/mockData.ts", "source_location": null, "source_url": null, "captured_at": null, "author": null, "contributor": null}, {"id": "mockData_DashboardStats", "label": "DashboardStats Interface", "file_type": "code", "source_file": "apps/desktop/src/lib/mockData.ts", "source_location": null, "source_url": null, "captured_at": null, "author": null, "contributor": null}, {"id": "mockData_NotificationItem", "label": "NotificationItem Interface", "file_type": "code", "source_file": "apps/desktop/src/lib/mockData.ts", "source_location": null, "source_url": null, "captured_at": null, "author": null, "contributor": null}, {"id": "mockData_ProfileSummary", "label": "ProfileSummary Interface", "file_type": "code", "source_file": "apps/desktop/src/lib/mockData.ts", "source_location": null, "source_url": null, "captured_at": null, "author": null, "contributor": null}, {"id": "mockData_MapViewMarker", "label": "MapViewMarker Interface", "file_type": "code", "source_file": "apps/desktop/src/lib/mockData.ts", "source_location": null, "source_url": null, "captured_at": null, "author": null, "contributor": null}, {"id": "mockData_MapViewSummary", "label": "MapViewSummary Interface", "file_type": "code", "source_file": "apps/desktop/src/lib/mockData.ts", "source_location": null, "source_url": null, "captured_at": null, "author": null, "contributor": null}, {"id": "mockData_MOCK_ASSESSMENTS", "label": "Mock Assessments Data", "file_type": "code", "source_file": "apps/desktop/src/lib/mockData.ts", "source_location": null, "source_url": null, "captured_at": null, "author": null, "contributor": null}, {"id": "mockData_MOCK_NOTIFICATIONS", "label": "Mock Notifications Data", "file_type": "code", "source_file": "apps/desktop/src/lib/mockData.ts", "source_location": null, "source_url": null, "captured_at": null, "author": null, "contributor": null}, {"id": "mockData_PROFILE_SUMMARY", "label": "Profile Summary Data", "file_type": "code", "source_file": "apps/desktop/src/lib/mockData.ts", "source_location": null, "source_url": null, "captured_at": null, "author": null, "contributor": null}, {"id": "mockData_DASHBOARD_MAP_MARKERS", "label": "Dashboard Map Markers Data", "file_type": "code", "source_file": "apps/desktop/src/lib/mockData.ts", "source_location": null, "source_url": null, "captured_at": null, "author": null, "contributor": null}, {"id": "mockData_MAP_VIEW_MARKERS", "label": "Map View Markers Data", "file_type": "code", "source_file": "apps/desktop/src/lib/mockData.ts", "source_location": null, "source_url": null, "captured_at": null, "author": null, "contributor": null}, {"id": "mockData_MOCK_FRAMES_BY_ASSESSMENT_ID", "label": "Mock Frames By Assessment ID", "file_type": "code", "source_file": "apps/desktop/src/lib/mockData.ts", "source_location": null, "source_url": null, "captured_at": null, "author": null, "contributor": null}, {"id": "mockData_MOCK_REPORT_BY_ASSESSMENT_ID", "label": "Mock Report By Assessment ID", "file_type": "code", "source_file": "apps/desktop/src/lib/mockData.ts", "source_location": null, "source_url": null, "captured_at": null, "author": null, "contributor": null}, {"id": "mockData_generateFrames", "label": "Generate Frames Function", "file_type": "code", "source_file": "apps/desktop/src/lib/mockData.ts", "source_location": null, "source_url": null, "captured_at": null, "author": null, "contributor": null}], "edges": [{"source": "mockData_generateFrames", "target": "mockData_MOCK_FRAMES_BY_ASSESSMENT_ID", "relation": "calls", "confidence": "EXTRACTED", "confidence_score": 1.0, "source_file": "apps/desktop/src/lib/mockData.ts", "source_location": null, "weight": 1.0}], "hyperedges": []}