{"nodes": [{"id": "c_users_frank_desktop_projects_aegis_apps_desktop_src_components_workspace_videoplayer_tsx", "label": "VideoPlayer.tsx", "file_type": "code", "source_file": "C:\\Users\\Frank\\Desktop\\PROJECTS\\aegis\\apps\\desktop\\src\\components\\workspace\\VideoPlayer.tsx", "source_location": "L1"}, {"id": "videoplayer_formattime", "label": "formatTime()", "file_type": "code", "source_file": "C:\\Users\\Frank\\Desktop\\PROJECTS\\aegis\\apps\\desktop\\src\\components\\workspace\\VideoPlayer.tsx", "source_location": "L17"}, {"id": "videoplayer_onloaded", "label": "onLoaded()", "file_type": "code", "source_file": "C:\\Users\\Frank\\Desktop\\PROJECTS\\aegis\\apps\\desktop\\src\\components\\workspace\\VideoPlayer.tsx", "source_location": "L57"}, {"id": "videoplayer_ontime", "label": "onTime()", "file_type": "code", "source_file": "C:\\Users\\Frank\\Desktop\\PROJECTS\\aegis\\apps\\desktop\\src\\components\\workspace\\VideoPlayer.tsx", "source_location": "L66"}, {"id": "videoplayer_onplay", "label": "onPlay()", "file_type": "code", "source_file": "C:\\Users\\Frank\\Desktop\\PROJECTS\\aegis\\apps\\desktop\\src\\components\\workspace\\VideoPlayer.tsx", "source_location": "L71"}, {"id": "videoplayer_onpause", "label": "onPause()", "file_type": "code", "source_file": "C:\\Users\\Frank\\Desktop\\PROJECTS\\aegis\\apps\\desktop\\src\\components\\workspace\\VideoPlayer.tsx", "source_location": "L72"}], "edges": [{"source": "c_users_frank_desktop_projects_aegis_apps_desktop_src_components_workspace_videoplayer_tsx", "target": "lucide_react", "relation": "imports_from", "confidence": "EXTRACTED", "source_file": "C:\\Users\\Frank\\Desktop\\PROJECTS\\aegis\\apps\\desktop\\src\\components\\workspace\\VideoPlayer.tsx", "source_location": "L1", "weight": 1.0}, {"source": "c_users_frank_desktop_projects_aegis_apps_desktop_src_components_workspace_videoplayer_tsx", "target": "react", "relation": "imports_from", "confidence": "EXTRACTED", "source_file": "C:\\Users\\Frank\\Desktop\\PROJECTS\\aegis\\apps\\desktop\\src\\components\\workspace\\VideoPlayer.tsx", "source_location": "L2", "weight": 1.0}, {"source": "c_users_frank_desktop_projects_aegis_apps_desktop_src_components_workspace_videoplayer_tsx", "target": "c_users_frank_desktop_projects_aegis_apps_desktop_src_components_ui_brandedloader", "relation": "imports_from", "confidence": "EXTRACTED", "source_file": "C:\\Users\\Frank\\Desktop\\PROJECTS\\aegis\\apps\\desktop\\src\\components\\workspace\\VideoPlayer.tsx", "source_location": "L3", "weight": 1.0}, {"source": "c_users_frank_desktop_projects_aegis_apps_desktop_src_components_workspace_videoplayer_tsx", "target": "videoplayer_formattime", "relation": "contains", "confidence": "EXTRACTED", "source_file": "C:\\Users\\Frank\\Desktop\\PROJECTS\\aegis\\apps\\desktop\\src\\components\\workspace\\VideoPlayer.tsx", "source_location": "L17", "weight": 1.0}, {"source": "c_users_frank_desktop_projects_aegis_apps_desktop_src_components_workspace_videoplayer_tsx", "target": "videoplayer_onloaded", "relation": "contains", "confidence": "EXTRACTED", "source_file": "C:\\Users\\Frank\\Desktop\\PROJECTS\\aegis\\apps\\desktop\\src\\components\\workspace\\VideoPlayer.tsx", "source_location": "L57", "weight": 1.0}, {"source": "c_users_frank_desktop_projects_aegis_apps_desktop_src_components_workspace_videoplayer_tsx", "target": "videoplayer_ontime", "relation": "contains", "confidence": "EXTRACTED", "source_file": "C:\\Users\\Frank\\Desktop\\PROJECTS\\aegis\\apps\\desktop\\src\\components\\workspace\\VideoPlayer.tsx", "source_location": "L66", "weight": 1.0}, {"source": "c_users_frank_desktop_projects_aegis_apps_desktop_src_components_workspace_videoplayer_tsx", "target": "videoplayer_onplay", "relation": "contains", "confidence": "EXTRACTED", "source_file": "C:\\Users\\Frank\\Desktop\\PROJECTS\\aegis\\apps\\desktop\\src\\components\\workspace\\VideoPlayer.tsx", "source_location": "L71", "weight": 1.0}, {"source": "c_users_frank_desktop_projects_aegis_apps_desktop_src_components_workspace_videoplayer_tsx", "target": "videoplayer_onpause", "relation": "contains", "confidence": "EXTRACTED", "source_file": "C:\\Users\\Frank\\Desktop\\PROJECTS\\aegis\\apps\\desktop\\src\\components\\workspace\\VideoPlayer.tsx", "source_location": "L72", "weight": 1.0}], "raw_calls": [{"caller_nid": "videoplayer_formattime", "callee": "isFinite", "source_file": "C:\\Users\\Frank\\Desktop\\PROJECTS\\aegis\\apps\\desktop\\src\\components\\workspace\\VideoPlayer.tsx", "source_location": "L18"}, {"caller_nid": "videoplayer_formattime", "callee": "floor", "source_file": "C:\\Users\\Frank\\Desktop\\PROJECTS\\aegis\\apps\\desktop\\src\\components\\workspace\\VideoPlayer.tsx", "source_location": "L19"}, {"caller_nid": "videoplayer_formattime", "callee": "floor", "source_file": "C:\\Users\\Frank\\Desktop\\PROJECTS\\aegis\\apps\\desktop\\src\\components\\workspace\\VideoPlayer.tsx", "source_location": "L20"}, {"caller_nid": "videoplayer_formattime", "callee": "padStart", "source_file": "C:\\Users\\Frank\\Desktop\\PROJECTS\\aegis\\apps\\desktop\\src\\components\\workspace\\VideoPlayer.tsx", "source_location": "L21"}, {"caller_nid": "videoplayer_formattime", "callee": "toString", "source_file": "C:\\Users\\Frank\\Desktop\\PROJECTS\\aegis\\apps\\desktop\\src\\components\\workspace\\VideoPlayer.tsx", "source_location": "L21"}, {"caller_nid": "videoplayer_onloaded", "callee": "setDuration", "source_file": "C:\\Users\\Frank\\Desktop\\PROJECTS\\aegis\\apps\\desktop\\src\\components\\workspace\\VideoPlayer.tsx", "source_location": "L58"}, {"caller_nid": "videoplayer_onloaded", "callee": "catch", "source_file": "C:\\Users\\Frank\\Desktop\\PROJECTS\\aegis\\apps\\desktop\\src\\components\\workspace\\VideoPlayer.tsx", "source_location": "L61"}, {"caller_nid": "videoplayer_onloaded", "callee": "play", "source_file": "C:\\Users\\Frank\\Desktop\\PROJECTS\\aegis\\apps\\desktop\\src\\components\\workspace\\VideoPlayer.tsx", "source_location": "L61"}, {"caller_nid": "videoplayer_ontime", "callee": "setCurrent", "source_file": "C:\\Users\\Frank\\Desktop\\PROJECTS\\aegis\\apps\\desktop\\src\\components\\workspace\\VideoPlayer.tsx", "source_location": "L68"}, {"caller_nid": "videoplayer_ontime", "callee": "onTimeUpdate", "source_file": "C:\\Users\\Frank\\Desktop\\PROJECTS\\aegis\\apps\\desktop\\src\\components\\workspace\\VideoPlayer.tsx", "source_location": "L69"}, {"caller_nid": "videoplayer_onplay", "callee": "setPlaying", "source_file": "C:\\Users\\Frank\\Desktop\\PROJECTS\\aegis\\apps\\desktop\\src\\components\\workspace\\VideoPlayer.tsx", "source_location": "L71"}, {"caller_nid": "videoplayer_onpause", "callee": "setPlaying", "source_file": "C:\\Users\\Frank\\Desktop\\PROJECTS\\aegis\\apps\\desktop\\src\\components\\workspace\\VideoPlayer.tsx", "source_location": "L72"}]}